Metadata-Version: 2.1
Name: radare2
Version: 5.9.1
Summary: The UNIX friendly reverse engineering framework and toolchain
Home-page: https://www.radare.org/
Author: pancake
Author-email: pancake@nopcode.org
Requires-Dist: r2pipe
Requires-Dist: r2env
